gocadgo/__init__.py
gocadgo/cell.py
gocadgo/hello.py
gocadgo/helper.py
gocadgo/main.py
gocadgo/network.py
gocadgo/plotter.py
gocadgo-2.0.0.dist-info/LICENSE
gocadgo-2.0.0.dist-info/METADATA
gocadgo-2.0.0.dist-info/WHEEL
gocadgo-2.0.0.dist-info/top_level.txt
gocadgo-2.0.0.dist-info/RECORD
