Metadata-Version: 2.1
Name: gocadgo
Version: 2.0.0
Summary: A basic network-based solver to propagate through heat exchanger cell properties
Author: Marina Kovaleva
License: MIT
Project-URL: Homepage, https://github.com/marina8888/gocadgo
Project-URL: Bug Tracker, https://github.com/marina8888/gocadgo/issues
Keywords: cfd,heat-loss,heat-exchanger
Classifier: Development Status :: 1 - Planning
Classifier: Intended Audience :: Developers
Classifier: License :: OSI Approved :: MIT License
Classifier: Operating System :: MacOS
Classifier: Operating System :: Microsoft :: Windows
Classifier: Operating System :: POSIX
Classifier: Operating System :: Unix
Classifier: Programming Language :: Python :: 3
Classifier: Topic :: Other/Nonlisted Topic
Requires-Python: >=3
License-File: LICENSE
Requires-Dist: cffi>=1.0.0
Requires-Dist: matplotlib
Requires-Dist: numpy
Requires-Dist: Cantera
